tests/__init__.py
tests/test_activation.py
tests/test_adaptivepool.py
tests/test_batchnorm.py
tests/test_conv.py
tests/test_custom_matmul.py
tests/test_deconv.py
tests/test_depthwiseconv.py
tests/test_embedding.py
tests/test_extend.py
tests/test_globalpool.py
tests/test_groupconv2d.py
tests/test_layernorm.py
tests/test_linear.py
tests/test_mask_conv.py
tests/test_merge.py
tests/test_noise.py
tests/test_onnx.py
tests/test_padding.py
tests/test_pool.py
tests/test_rnn.py
tests/test_sampling.py
tests/test_scale.py
tests/test_shape.py
tests/test_stack.py
tests/test_subpixelconv.py
tests/test_topology.py
tests/export_application/__init__.py
tests/export_application/imagenet_classes.py
tests/export_application/test_export_srgan.py
tests/export_application/test_export_vgg16.py
tlx2onnx/__init__.py
tlx2onnx/main.py
tlx2onnx/topology.py
tlx2onnx/common/__init__.py
tlx2onnx/common/onnx_tool.py
tlx2onnx/common/preprocessing.py
tlx2onnx/common/utils.py
tlx2onnx/op_mapper/__init__.py
tlx2onnx/op_mapper/activation.py
tlx2onnx/op_mapper/datatype_mapping.py
tlx2onnx/op_mapper/op_mapper.py
tlx2onnx/op_mapper/tensor.py
tlx2onnx/op_mapper/math/__init__.py
tlx2onnx/op_mapper/math/add.py
tlx2onnx/op_mapper/math/matmul.py
tlx2onnx/op_mapper/nn/__init__.py
tlx2onnx/op_mapper/nn/adaptivepool.py
tlx2onnx/op_mapper/nn/conv.py
tlx2onnx/op_mapper/nn/deconv.py
tlx2onnx/op_mapper/nn/dropout.py
tlx2onnx/op_mapper/nn/dwconv.py
tlx2onnx/op_mapper/nn/embedding.py
tlx2onnx/op_mapper/nn/extend.py
tlx2onnx/op_mapper/nn/flatten.py
tlx2onnx/op_mapper/nn/globalpool.py
tlx2onnx/op_mapper/nn/groupconv.py
tlx2onnx/op_mapper/nn/linear.py
tlx2onnx/op_mapper/nn/mask_conv.py
tlx2onnx/op_mapper/nn/merge.py
tlx2onnx/op_mapper/nn/noise.py
tlx2onnx/op_mapper/nn/normalization.py
tlx2onnx/op_mapper/nn/padding.py
tlx2onnx/op_mapper/nn/pool.py
tlx2onnx/op_mapper/nn/resampling.py
tlx2onnx/op_mapper/nn/rnn.py
tlx2onnx/op_mapper/nn/scale.py
tlx2onnx/op_mapper/nn/shape.py
tlx2onnx/op_mapper/nn/stack.py
tlx2onnx-0.0.2.dist-info/LICENSE
tlx2onnx-0.0.2.dist-info/METADATA
tlx2onnx-0.0.2.dist-info/WHEEL
tlx2onnx-0.0.2.dist-info/top_level.txt
tlx2onnx-0.0.2.dist-info/RECORD
